solum_tempest_plugin/__init__.py
solum_tempest_plugin/base.py
solum_tempest_plugin/config.py
solum_tempest_plugin/plugin.py
solum_tempest_plugin/common/__init__.py
solum_tempest_plugin/common/apputils.py
solum_tempest_plugin/tests/__init__.py
solum_tempest_plugin/tests/application_deployment/__init__.py
solum_tempest_plugin/tests/application_deployment/test_versions.py
solum_tempest_plugin/tests/application_deployment/camp/__init__.py
solum_tempest_plugin/tests/application_deployment/camp/test_platform_endpoints.py
solum_tempest_plugin/tests/application_deployment/camp/v1_1/__init__.py
solum_tempest_plugin/tests/application_deployment/camp/v1_1/test_assemblies.py
solum_tempest_plugin/tests/application_deployment/camp/v1_1/test_formats.py
solum_tempest_plugin/tests/application_deployment/camp/v1_1/test_parameter_definitions.py
solum_tempest_plugin/tests/application_deployment/camp/v1_1/test_plans.py
solum_tempest_plugin/tests/application_deployment/camp/v1_1/test_platform.py
solum_tempest_plugin/tests/application_deployment/camp/v1_1/test_type_definitions.py
solum_tempest_plugin/tests/application_deployment/v1/__init__.py
solum_tempest_plugin/tests/application_deployment/v1/test_app.py
solum_tempest_plugin/tests/application_deployment/v1/test_assembly.py
solum_tempest_plugin/tests/application_deployment/v1/test_component.py
solum_tempest_plugin/tests/application_deployment/v1/test_extension.py
solum_tempest_plugin/tests/application_deployment/v1/test_language_pack.py
solum_tempest_plugin/tests/application_deployment/v1/test_operation.py
solum_tempest_plugin/tests/application_deployment/v1/test_plan.py
solum_tempest_plugin/tests/application_deployment/v1/test_root.py
solum_tempest_plugin/tests/application_deployment/v1/test_sensor.py
solum_tempest_plugin/tests/application_deployment/v1/test_service.py
solum_tempest_plugin/tests/application_deployment/v1/public/__init__.py
solum_tempest_plugin/tests/application_deployment/v1/public/test_trigger.py
solum_tempest_plugin-2.7.0.dist-info/AUTHORS
solum_tempest_plugin-2.7.0.dist-info/LICENSE
solum_tempest_plugin-2.7.0.dist-info/METADATA
solum_tempest_plugin-2.7.0.dist-info/WHEEL
solum_tempest_plugin-2.7.0.dist-info/entry_points.txt
solum_tempest_plugin-2.7.0.dist-info/pbr.json
solum_tempest_plugin-2.7.0.dist-info/top_level.txt
solum_tempest_plugin-2.7.0.dist-info/RECORD
